{
  "main": {
    "id": "a1725fcf46247412",
    "type": "split",
    "children": [
      {
        "id": "f16222d8978979be",
        "type": "tabs",
        "children": [
          {
            "id": "79d27fdf09e3d4f3",
            "type": "leaf",
            "state": {
              "type": "markdown",
              "state": {
                "file": "计算机学习/acwing-Linux/1. 常用文件管理命令.md",
                "mode": "preview",
                "source": false
              }
            }
          },
          {
            "id": "597bb7b74c1639fb",
            "type": "leaf",
            "state": {
              "type": "markdown",
              "state": {
                "file": "Personal Arrangement/Daily/2024/2024-03/2024-03-05_星期二.md",
                "mode": "source",
                "source": false
              }
            }
          },
          {
            "id": "07a16d6d1500f7ab",
            "type": "leaf",
            "state": {
              "type": "markdown",
              "state": {
                "file": "教资学习/科目二 教育知识与能力.md",
                "mode": "source",
                "source": false
              }
            }
          },
          {
            "id": "906d4f61d962c033",
            "type": "leaf",
            "state": {
              "type": "markdown",
              "state": {
                "file": "教资学习/科目二刷题.md",
                "mode": "source",
                "source": false
              }
            }
          },
          {
            "id": "59bed33c8d1813c5",
            "type": "leaf",
            "state": {
              "type": "markdown",
              "state": {
                "file": "Personal Arrangement/Templates/001-Daily模板.md",
                "mode": "source",
                "source": false
              }
            }
          }
        ],
        "currentTab": 3
      }
    ],
    "direction": "vertical"
  },
  "left": {
    "id": "44e9bdfcdd8514c4",
    "type": "split",
    "children": [
      {
        "id": "288b1a7d5f0a7819",
        "type": "tabs",
        "children": [
          {
            "id": "47e0aaa898b2419f",
            "type": "leaf",
            "state": {
              "type": "file-explorer",
              "state": {
                "sortOrder": "alphabetical"
              }
            }
          },
          {
            "id": "a1e47bfd0d6b27b2",
            "type": "leaf",
            "state": {
              "type": "search",
              "state": {
                "query": "",
                "matchingCase": false,
                "explainSearch": false,
                "collapseAll": false,
                "extraContext": false,
                "sortOrder": "alphabetical"
              }
            }
          },
          {
            "id": "64642864beda1e07",
            "type": "leaf",
            "state": {
              "type": "starred",
              "state": {}
            }
          },
          {
            "id": "7afdef0fced9cd14",
            "type": "leaf",
            "state": {
              "type": "bookmarks",
              "state": {}
            }
          }
        ]
      }
    ],
    "direction": "horizontal",
    "width": 200
  },
  "right": {
    "id": "8187cdb355ff2fe1",
    "type": "split",
    "children": [
      {
        "id": "4a270382dd0f6392",
        "type": "tabs",
        "children": [
          {
            "id": "39d287893156fb13",
            "type": "leaf",
            "state": {
              "type": "backlink",
              "state": {
                "file": "教资学习/科目二刷题.md",
                "collapseAll": false,
                "extraContext": false,
                "sortOrder": "alphabetical",
                "showSearch": false,
                "searchQuery": "",
                "backlinkCollapsed": false,
                "unlinkedCollapsed": true
              }
            }
          },
          {
            "id": "dd7a4a6c30582273",
            "type": "leaf",
            "state": {
              "type": "outgoing-link",
              "state": {
                "file": "教资学习/科目二刷题.md",
                "linksCollapsed": false,
                "unlinkedCollapsed": true
              }
            }
          },
          {
            "id": "d2db25438785443c",
            "type": "leaf",
            "state": {
              "type": "tag",
              "state": {
                "sortOrder": "frequency",
                "useHierarchy": true
              }
            }
          },
          {
            "id": "02e6ab9ff3ebb8e9",
            "type": "leaf",
            "state": {
              "type": "outline",
              "state": {
                "file": "教资学习/科目二刷题.md"
              }
            }
          }
        ],
        "currentTab": 3
      }
    ],
    "direction": "horizontal",
    "width": 300,
    "collapsed": true
  },
  "left-ribbon": {
    "hiddenItems": {
      "canvas:新建白板": false,
      "switcher:打开快速切换": false,
      "graph:查看关系图谱": false,
      "command-palette:打开命令面板": false,
      "publish:发布更改": false,
      "daily-notes:打开/创建今天的日记": false,
      "templates:插入模板": false
    }
  },
  "active": "906d4f61d962c033",
  "lastOpenFiles": [
    "Personal Arrangement/Templates/001-Daily模板.md",
    "教资学习/科目二刷题.md",
    "Personal Arrangement/Daily/2024/2024-03/2024-03-05_星期二.md",
    "Personal Arrangement/Daily/2024/2024-03/2024-03-04_星期一.md",
    "教资学习/科目二 教育知识与能力.md",
    "未命名.md",
    "计算机学习/acwing-Linux/1. 常用文件管理命令.md",
    "教资学习",
    "计算机学习/C++基础/C++ Grammer.md",
    "Personal Arrangement/Daily/2024/2024-03",
    "Personal Arrangement/Daily/2024",
    "Personal Arrangement/Templates",
    "Personal Arrangement/Daily",
    "Personal Arrangement",
    "计算机学习",
    "计算机学习/Computer Networking/CH1 计算机网络概述.md",
    "计算机学习/Computer Networking",
    "计算机学习/oeasy-Python/Python笔记.md",
    "计算机学习/acwing-Linux",
    "计算机学习/oeasy-Linux/Linux笔记.md",
    "计算机学习/C++基础/Practices.md",
    "计算机学习/C++基础",
    "计算机学习/oeasy-Linux/photo for Linux/Pasted image 20230306102619.png",
    "计算机学习/oeasy-Linux/photo for Linux/L8-3.png",
    "计算机学习/oeasy-Linux/photo for Linux/L8-2.png",
    "计算机学习/oeasy-Linux/photo for Linux/L7-3.png",
    "oeasy-Linux/photo for Linux/Pasted image 20230223110607.png",
    "计算机学习/oeasy-Linux/photo for Linux/L6-3.png",
    "oeasy-Linux/photo for Linux/Pasted image 20230222215613.png",
    "计算机学习/oeasy-Linux/photo for Linux/L6-1.jpg",
    "photo.md",
    "未命名.canvas"
  ]
}